ya_ecs_ctl/__init__.py
ya_ecs_ctl/main.py
ya_ecs_ctl/utils.py
ya_ecs_ctl-0.3.9.dist-info/LICENSE
ya_ecs_ctl-0.3.9.dist-info/METADATA
ya_ecs_ctl-0.3.9.dist-info/WHEEL
ya_ecs_ctl-0.3.9.dist-info/entry_points.txt
ya_ecs_ctl-0.3.9.dist-info/top_level.txt
ya_ecs_ctl-0.3.9.dist-info/RECORD
