Metadata-Version: 2.1
Name: ya-ecs-ctl
Version: 0.3.9
Summary: AWS ECS Control Tool
Home-page: https://github.com/hampsterx/ya-ecs-ctl
Author: Tim van der Hulst
Author-email: tim.vdh@gmail.com
License: Apache2
Classifier: Development Status :: 4 - Beta
Classifier: Intended Audience :: System Administrators
Classifier: License :: OSI Approved :: Apache Software License
Classifier: Programming Language :: Python :: 2
License-File: LICENSE
Requires-Dist: click >=6.6
Requires-Dist: boto3 <2,>=1.30
Requires-Dist: terminaltables ==3.1.0
Requires-Dist: humanize ==0.5.1
Requires-Dist: EasySettings ==2.1.0
Requires-Dist: prompt-toolkit ==2.0.4
Requires-Dist: PyYAML >=6.0.1
Requires-Dist: colored ==1.3.5
Requires-Dist: Jinja2 >=2.8
